mattermostdriver/__init__.py
mattermostdriver/client.py
mattermostdriver/driver.py
mattermostdriver/exceptions.py
mattermostdriver/version.py
mattermostdriver/websocket.py
mattermostdriver/endpoints/__init__.py
mattermostdriver/endpoints/base.py
mattermostdriver/endpoints/brand.py
mattermostdriver/endpoints/channels.py
mattermostdriver/endpoints/cluster.py
mattermostdriver/endpoints/commands.py
mattermostdriver/endpoints/compliance.py
mattermostdriver/endpoints/data_retention.py
mattermostdriver/endpoints/elasticsearch.py
mattermostdriver/endpoints/emoji.py
mattermostdriver/endpoints/files.py
mattermostdriver/endpoints/ldap.py
mattermostdriver/endpoints/oauth.py
mattermostdriver/endpoints/posts.py
mattermostdriver/endpoints/preferences.py
mattermostdriver/endpoints/saml.py
mattermostdriver/endpoints/system.py
mattermostdriver/endpoints/teams.py
mattermostdriver/endpoints/users.py
mattermostdriver/endpoints/webhooks.py
mattermostdriver_asyncio-5.0.1.dist-info/DESCRIPTION.rst
mattermostdriver_asyncio-5.0.1.dist-info/METADATA
mattermostdriver_asyncio-5.0.1.dist-info/RECORD
mattermostdriver_asyncio-5.0.1.dist-info/WHEEL
mattermostdriver_asyncio-5.0.1.dist-info/metadata.json
mattermostdriver_asyncio-5.0.1.dist-info/top_level.txt
