Metadata-Version: 2.0
Name: mattermostdriver-asyncio
Version: 5.0.1
Summary: An asyncio Python Mattermost Driver
Home-page: UNKNOWN
Author: Nate Mara
Author-email: nate.mara@kroger.com
License: MIT
Platform: UNKNOWN
Classifier: Development Status :: 5 - Production/Stable
Classifier: Environment :: Web Environment
Classifier: Intended Audience :: Developers
Classifier: Programming Language :: Python
Classifier: Programming Language :: Python :: 3
Classifier: Programming Language :: Python :: 3.4
Classifier: Programming Language :: Python :: 3.5
Classifier: Programming Language :: Python :: 3.6
Requires-Dist: aiodns (>=1.1.1)
Requires-Dist: aiohttp (>=2.3.4)
Requires-Dist: async-timeout (>=1.4.0)
Requires-Dist: cchardet (>=2.1.1)
Requires-Dist: websockets (>=3.2)
